tests
shield
