Metadata-Version: 1.1
Name: shield
Version: 0.3.1
Summary: A permissions framework built around declarative rules.
Home-page: http://github.com/concordusapps/python-shield
Author: Concordus Applications
Author-email: support@concordusapps.com
License: MIT
Platform: UNKNOWN
Classifier: Development Status :: 3 - Alpha
Classifier: Intended Audience :: Developers
Classifier: License :: OSI Approved :: MIT License
Classifier: Operating System :: OS Independent
Classifier: Programming Language :: Python :: 2.7
Classifier: Programming Language :: Python :: 3.3
